MANIFEST.in
setup.cfg
setup.py
ubm/.DS_Store
ubm/__init__.py
ubm.egg-info/PKG-INFO
ubm.egg-info/SOURCES.txt
ubm.egg-info/dependency_links.txt
ubm.egg-info/requires.txt
ubm.egg-info/top_level.txt
ubm/__pycache__/__init__.cpython-35.pyc
ubm/__pycache__/__init__.cpython-36.pyc
ubm/acquisition/.DS_Store
ubm/acquisition/__init__.py
ubm/acquisition/acquisition.py
ubm/acquisition/filter.py
ubm/acquisition/__pycache__/__init__.cpython-35.pyc
ubm/acquisition/__pycache__/__init__.cpython-36.pyc
ubm/acquisition/__pycache__/acquisition.cpython-35.pyc
ubm/acquisition/__pycache__/acquisition.cpython-36.pyc
ubm/acquisition/__pycache__/filter.cpython-35.pyc
ubm/acquisition/__pycache__/filter.cpython-36.pyc
ubm/acquisition/dataset/.DS_Store
ubm/acquisition/dataset/__init__.py
ubm/acquisition/dataset/dataset.py
ubm/acquisition/dataset/names.py
ubm/acquisition/dataset/__pycache__/__init__.cpython-35.pyc
ubm/acquisition/dataset/__pycache__/__init__.cpython-36.pyc
ubm/acquisition/dataset/__pycache__/dataset.cpython-35.pyc
ubm/acquisition/dataset/__pycache__/dataset.cpython-36.pyc
ubm/acquisition/dataset/__pycache__/names.cpython-35.pyc
ubm/acquisition/dataset/__pycache__/names.cpython-36.pyc
ubm/acquisition/dataset/__pycache__-IngBook/Dataset.cpython-35.pyc
ubm/acquisition/dataset/__pycache__-IngBook/__init__.cpython-35.pyc
ubm/acquisition/dataset/components/.DS_Store
ubm/acquisition/dataset/components/__init__.py
ubm/acquisition/dataset/components/driver.py
ubm/acquisition/dataset/components/engine.py
ubm/acquisition/dataset/components/imu.py
ubm/acquisition/dataset/components/internal.py
ubm/acquisition/dataset/components/vehicle.py
ubm/acquisition/dataset/components/__pycache__/__init__.cpython-35.pyc
ubm/acquisition/dataset/components/__pycache__/__init__.cpython-36.pyc
ubm/acquisition/dataset/components/__pycache__/driver.cpython-35.pyc
ubm/acquisition/dataset/components/__pycache__/driver.cpython-36.pyc
ubm/acquisition/dataset/components/__pycache__/imu.cpython-35.pyc
ubm/acquisition/dataset/components/__pycache__/imu.cpython-36.pyc
ubm/acquisition/dataset/components/__pycache__/internal.cpython-35.pyc
