Metadata-Version: 1.1
Name: ubm
Version: 1.0.4
Summary: Library for UniBo Motorsport data analysis
Home-page: https://github.com/Ax6/ubm-python-libraries
Author: Aaron Russo
Author-email: axolo6@gmail.com
License: UNKNOWN
Download-URL: https://github.com/Ax6/ubm-python-libraries/archive/v1.0.4.tar.gz
Platform: UNKNOWN
